HISTORY.txt
README.txt
TODO.txt
setup.cfg
setup.py
prdg/__init__.py
prdg.util.egg-info/PKG-INFO
prdg.util.egg-info/SOURCES.txt
prdg.util.egg-info/dependency_links.txt
prdg.util.egg-info/entry_points.txt
prdg.util.egg-info/namespace_packages.txt
prdg.util.egg-info/not-zip-safe
prdg.util.egg-info/requires.txt
prdg.util.egg-info/top_level.txt
prdg/util/__init__.py
prdg/util/datastructures.py
prdg/util/decorators.py
prdg/util/emails.py
prdg/util/file.py
prdg/util/path.py
prdg/util/proc.py
prdg/util/strings.py
prdg/util/testing.py
prdg/util/url.py