Metadata-Version: 1.0
Name: prdg.util
Version: 0.0.7
Summary: General utilities.
Home-page: http://code.google.com/p/prdg-python/
Author: Rafael Oliveira
Author-email: rafaelbco@gmail.com
License: GPL
Keywords: util utils
Platform: UNKNOWN
Classifier: Programming Language :: Python
Classifier: Topic :: Software Development :: Libraries :: Python Modules
